Workbook

Sheet Original_Data
A1: store_id | B1: month | C1: region | D1: store_type | E1: marketing_spend | F1: footfall | G1: avg_discount_pct | H1: staff_count | I1: inventory_availability_pct | J1: competitor_distance_km | K1: holiday_flag | L1: customer_rating | M1: monthly_sales | N1: monthly_profit
A2: STR-1001 | B2: 45658 | C2: East | D2: Residential | E2: 70389.11 | F2: 8302 | G2: 0.042 | H2: 17 | I2: 75 | J2: 5.28 | K2: 1 | L2: 3.1 | M2: 658832.62 | N2: 84349.93
A3: STR-1001 | B3: 45689 | C3: East | D3: Residential | E3: 43827.89 | F3: 8487 | G3: 0.168 | H3: 23 | I3: 84.4 | J3: 4.31 | K3: 0 | L3: 2.8 | M3: 634436 | N3: 106130.54
A4: STR-1001 | B4: 45717 | C4: East | D4: Residential | E4: 59921.75 | F4: 9113 | G4: 0.133 | H4: 20 | I4: 88 | J4: 12 | K4: 0 | L4: 3.2 | M4: 678722.06 | N4: 101883.86
A5: STR-1001 | B5: 45748 | C5: East | D5: Residential | E5: 56856.63 | F5: 9431 | G5: 0.142 | H5: 23 | I5: 86.9 | J5: 4.97 | K5: 0 | L5: 3.4 | M5: 658920.3 | N5: 97910.37
A6: STR-1002 | B6: 45658 | C6: East | D6: High Street | E6: 48412.64 | F6: 9545 | G6: 0.231 | H6: 21 | I6: 97.6 | J6: 6.94 | K6: 1 | L6: 4.2 | M6: 741341.44 | N6: 119208.17
A7: STR-1002 | B7: 45689 | C7: East | D7: High Street | E7: 64811.21 | F7: 9792 | G7: 0.112 | H7: 20 | I7: 84.2 | J7: 2.88 | K7: 0 | L7: 4.2 | M7: 761835.34 | N7: 149602.23
A8: STR-1002 | B8: 45717 | C8: East | D8: High Street | E8: 46213.45 | F8: 10616 | G8: 0.122 | H8: 22 | I8: 85.2 | J8: 0.2 | K8: 1 | L8: 4.1 | M8: 806615.54 | N8: 131364.62
A9: STR-1002 | B9: 45748 | C9: East | D9: High Street | E9: 68148.52 | F9: 8567 | G9: 0.127 | H9: 23 | I9: 95.6 | J9: 0.8 | K9: 0 | L9: 3.9 | M9: 850164.26 | N9: 149262.75
A10: STR-1003 | B10: 45658 | C10: North | D10: Airport | E10: 71838.86 | F10: 10979 | G10: 0.215 | H10: 26 | I10: 88.6 | J10: 7.7 | K10: 1 | L10: 3.8 | M10: 930581.7 | N10: 136207.98
A11: STR-1003 | B11: 45689 | C11: North | D11: Airport | E11: 68133.44 | F11: 9459 | G11: 0.22 | H11: 21 | I11: 85 | J11: 1.91 | K11: 0 | L11: 4.2 | M11: 779010.94 | N11: 106328.09
A12: STR-1003 | B12: 45717 | C12: North | D12: Airport | E12: 34285.21 | F12: 9172 | G12: 0.213 | H12: 22 | I12: 88.3 | J12: 10.46 | K12: 1 | L12: 3.8 | M12: 723060.76 | N12: 123131.24
A13: STR-1003 | B13: 45748 | C13: North | D13: Airport | E13: 67979.88 | F13: 11230 | G13: 0.002 | H13: 28 | I13: 85.3 | J13: 7.16 | K13: 0 | L13: 3.8 | M13: 910791.94 | N13: 158891.28
... A34: STR-1009 | B34: 45658 | C34: North | D34: Residential | E34: 54597.83 | F34: 9429 | G34: 0.188 | H34: 21 | I34: 83.3 | J34: 11.71 | K34: 0 | L34: 4.2 | M34: 641865.03 | N34: 81342.58
A35: STR-1009 | B35: 45689 | C35: North | D35: Residential | E35: 73771.91 | F35: 11695 | G35: 0.07 | H35: 25 | I35: 84.7 | J35: 0.62 | K35: 0 | M35: 799477.76 | N35: 164974.41
A36: STR-1009 | B36: 45717 | C36: North | D36: Residential | E36: 74413.88 | F36: 9449 | G36: 0.039 | H36: 23 | I36: 92.1 | J36: 2.12 | K36: 0 | L36: 3.5 | M36: 798952.17 | N36: 161499.04
A37: STR-1009 | B37: 45748 | C37: North | D37: Residential | E37: 52483.77 | F37: 10453 | G37: 0.247 | H37: 25 | I37: 99 | J37: 6.31 | K37: 0 | L37: 3.6 | M37: 800979.78 | N37: 149242.27
A38: STR-1010 | B38: 45658 | C38: North | D38: Mall | E38: 75269.87 | F38: 8838 | G38: 0.092 | H38: 21 | I38: 83.1 | J38: 9.56 | K38: 1 | L38: 4.2 | M38: 820593.93 | N38: 115860.06
A39: STR-1010 | B39: 45689 | C39: North | D39: Mall | E39: 61245.41 | F39: 8156 | G39: 0.156 | H39: 19 | I39: 92.9 | J39: 9.05 | K39: 0 | L39: 3.8 | M39: 718330.53 | N39: 93247.9
A40: STR-1010 | B40: 45717 | C40: North | D40: Mall | E40: 93381.26 | F40: 7562 | G40: 0.198 | H40: 19 | I40: 82.9 | J40: 5.05 | K40: 0 | L40: 4 | M40: 736633.4 | N40: 115654.66
A41: STR-1010 | B41: 45748 | C41: North | D41: Mall | E41: 65012.19 | F41: 9598 | G41: 0.085 | H41: 24 | I41: 98.3 | J41: 0.89 | K41: 0 | L41: 3.8 | M41: 828623.85 | N41: 167320.52
A42: STR-1011 | B42: 45658 | C42: East | D42: Mall | E42: 40462.94 | F42: 3660 | G42: 0.218 | H42: 11 | I42: 95.2 | J42: 5.57 | K42: 0 | L42: 4.4 | M42: 592195.85 | N42: 92291.56
A43: STR-1011 | B43: 45689 | C43: East | D43: Mall | E43: 46123.88 | F43: 3227 | G43: 0.143 | H43: 10 | I43: 75.4 | J43: 1.06 | K43: 0 | L43: 4.4 | M43: 532644.46 | N43: 60681.32
A44: STR-1011 | B44: 45717 | C44: East | D44: Mall | E44: 68077.54 | F44: 3360 | G44: 0.128 | H44: 14 | I44: 88.2 | J44: 1.24 | K44: 1 | L44: 4 | M44: 657429.18 | N44: 88919.74
A45: STR-1011 | B45: 45748 | C45: East | D45: Mall | E45: 64882.14 | F45: 3642 | G45: 0.019 | H45: 13 | I45: 87.8 | J45: 4.52 | K45: 0 | L45: 4.2 | M45: 605178 | N45: 106958.74
A46: STR-1012 | B46: 45658 | C46: West | D46: Residential | E46: 138855.51 | F46: 5145 | G46: 0.06 | H46: 17 | I46: 88.2 | J46: 9.58 | K46: 0 | L46: 3.2 | M46: 595467.6 | N46: 104276.46
A47: STR-1012 | B47: 45689 | C47: West | D47: Residential | E47: 63630.21 | F47: 4460 | G47: 0.235 | H47: 14 | I47: 98.6 | J47: 5.52 | K47: 0 | L47: 3.5 | M47: 599603.4 | N47: 112685.12
... A72: STR-1018 | B72: 45717 | C72: East | D72: High Street | E72: 60571.82 | F72: 3193 | G72: 0.197 | H72: 7 | I72: 99 | J72: 1.43 | K72: 0 | L72: 3.2 | M72: 605023.87 | N72: 98545.81
A73: STR-1018 | B73: 45748 | C73: East | D73: High Street | E73: 55081.16 | F73: 5485 | G73: 0.036 | H73: 12 | I73: 88 | K73: 0 | L73: 3.5 | M73: 674774.09 | N73: 141917.59
A74: STR-1019 | B74: 45658 | C74: East | D74: Residential | E74: 46201.46 | F74: 5918 | G74: 0.277 | H74: 13 | I74: 78.8 | J74: 4.91 | K74: 0 | L74: 4.5 | M74: 616069.41 | N74: 54453.99
A75: STR-1019 | B75: 45689 | C75: East | D75: Residential | E75: 53762.92 | F75: 6821 | G75: 0.066 | H75: 19 | I75: 94.6 | J75: 7.03 | K75: 0 | L75: 4.4 | M75: 630829.94 | N75: 117090.02
A76: STR-1019 | B76: 45717 | C76: East | D76: Residential | E76: 70144.78 | F76: 6806 | G76: 0.178 | H76: 20 | I76: 93.1 | J76: 0.28 | K76: 1 | L76: 4.3 | M76: 788087.68 | N76: 116803.42
A77: STR-1019 | B77: 45748 | C77: East | D77: Residential | E77: 58749.63 | F77: 8252 | G77: 0.203 | H77: 20 | I77: 85.2 | J77: 3.61 | K77: 0 | L77: 4.5 | M77: 680840.36 | N77: 68007.68
A78: STR-1020 | B78: 45658 | C78: South | D78: High Street | E78: 56973.18 | F78: 6662 | G78: 0.1 | H78: 15 | I78: 77.7 | J78: 7.52 | K78: 1 | L78: 3.2 | M78: 643657.47 | N78: 87022.45
A79: STR-1020 | B79: 45689 | C79: South | D79: High Street | E79: 54872.82 | F79: 5962 | G79: 0.064 | H79: 12 | I79: 85.4 | J79: 2.58 | K79: 0 | L79: 2.9 | M79: 691112.6 | N79: 109212.83
A80: STR-1020 | B80: 45717 | C80: South | D80: High Street | E80: 80562.81 | F80: 7470 | G80: 0.172 | H80: 16 | I80: 83.5 | J80: 2.29 | K80: 0 | L80: 3.3 | M80: 776922.17 | N80: 150701.93
A81: STR-1020 | B81: 45748 | C81: South | D81: High Street | E81: 77999.9 | F81: 5974 | G81: 0.252 | H81: 14 | I81: 81.3 | J81: 2.39 | K81: 0 | L81: 3.2 | M81: 636561.34 | N81: 93861.06
A82: STR-1021 | B82: 45658 | C82: West | D82: Mall | E82: 60881.01 | F82: 5410 | G82: 0.179 | H82: 15 | I82: 83.9 | J82: 5.24 | K82: 0 | L82: 4.6 | M82: 621369.58 | N82: 85493.64
A83: STR-1021 | B83: 45689 | C83: West | D83: Mall | E83: 60628.38 | F83: 4451 | G83: 0.095 | H83: 10 | I83: 89.6 | J83: 3.17 | K83: 0 | L83: 4.6 | M83: 682208.01 | N83: 110318.84
A84: STR-1021 | B84: 45717 | C84: West | D84: Mall | E84: 72731.14 | F84: 4644 | G84: 0.084 | H84: 15 | I84: 87.1 | J84: 2.66 | K84: 0 | L84: 4.6 | M84: 727241.86 | N84: 155810.3
A85: STR-1021 | B85: 45748 | C85: West | D85: Mall | E85: 36475.71 | F85: 3559 | G85: 0.03 | H85: 8 | I85: 83.6 | J85: 1.41 | K85: 0 | L85: 4.2 | M85: 569100.78 | N85: 104808.78
A86: STR-1022 | B86: 45658 | C86: West | D86: High Street | E86: 55388.11 | F86: 3091 | G86: 0.108 | H86: 7 | I86: 85.4 | J86: 7.34 | K86: 0 | L86: 4.9 | M86: 574436.29 | N86: 80271.99
A87: STR-1022 | B87: 45689 | C87: West | D87: High Street | E87: 88443.77 | F87: 4004 | G87: 0.206 | H87: 11 | I87: 91.9 | J87: 5.95 | K87: 0 | M87: 611766.72 | N87: 88275.61
A88: STR-1022 | B88: 45717 | C88: West | D88: High Street | E88: 78231.91 | F88: 3788 | G88: 0.059 | H88: 11 | I88: 88.5 | J88: 15.51 | K88: 0 | L88: 4.3 | M88: 614596.32 | N88: 131199.41
A89: STR-1022 | B89: 45748 | C89: West | D89: High Street | E89: 18996.32 | F89: 1260 | G89: 0.145 | H89: 9 | I89: 86.4 | J89: 4.31 | K89: 0 | L89: 4.6 | M89: 450711.92 | N89: 90043.76
A90: STR-1023 | B90: 45658 | C90: South | D90: Mall | E90: 50517.94 | F90: 7024 | G90: 0.029 | H90: 18 | I90: 79.2 | J90: 6.61 | K90: 1 | L90: 4.1 | M90: 711213.46 | N90: 105863.26
A91: STR-1023 | B91: 45689 | C91: South | D91: Mall | E91: 141540.29 | F91: 5400 | G91: 0.013 | H91: 12 | I91: 87 | J91: 4.26 | K91: 0 | L91: 4.5 | M91: 627171.9 | N91: 105772.75
A92: STR-1023 | B92: 45717 | C92: South | D92: Mall | E92: 82116.19 | F92: 5988 | G92: 0.04 | H92: 17 | I92: 91.8 | J92: 5.75 | K92: 0 | L92: 4.7 | M92: 739852.58 | N92: 129386.43
A93: STR-1023 | B93: 45748 | C93: South | D93: Mall | E93: 31207.51 | F93: 3701 | G93: 0.043 | H93: 11 | I93: 84.7 | J93: 0.33 | K93: 0 | L93: 4.3 | M93: 586307.22 | N93: 73927.85
A94: STR-1024 | B94: 45658 | C94: West | D94: Residential | E94: 38966.59 | F94: 4509 | G94: 0.194 | H94: 14 | I94: 91.1 | J94: 2.92 | K94: 0 | L94: 4.6 | M94: 585937.48 | N94: 82624.2
A95: STR-1024 | B95: 45689 | C95: West | D95: Residential | E95: 67439.3 | F95: 6477 | G95: 0 | H95: 16 | I95: 90.9 | J95: 1.64 | K95: 0 | L95: 4.5 | M95: 753473.55 | N95: 151527.22
A96: STR-1024 | B96: 45717 | C96: West | D96: Residential | E96: 86421.88 | F96: 7970 | G96: 0.073 | H96: 17 | I96: 91.3 | J96: 0.8 | K96: 0 | L96: 5 | M96: 838250.32 | N96: 122939.34
A97: STR-1024 | B97: 45748 | C97: West | D97: Residential | E97: 9534.65 | F97: 6057 | G97: 0.074 | H97: 15 | I97: 94.1 | J97: 5.79 | K97: 0 | L97: 4.5 | M97: 607898.12 | N97: 135404.85
A98: STR-1025 | B98: 45658 | C98: West | D98: Mall | E98: 61132.07 | F98: 6394 | G98: 0.163 | H98: 19 | I98: 91 | J98: 19.6 | K98: 0 | L98: 4.4 | M98: 691113.62 | N98: 135145.44
A99: STR-1025 | B99: 45689 | C99: West | D99: Mall | E99: 78839.39 | F99: 5150 | G99: 0.171 | H99: 13 | I99: 85.8 | J99: 7.57 | K99: 0 | L99: 4.3 | M99: 735509.4 | N99: 83895.96
A100: STR-1025 | B100: 45717 | C100: West | D100: Mall | E100: 38752.8 | F100: 4712 | G100: 0.075 | H100: 15 | I100: 89.7 | K100: 0 | L100: 4.3 | M100: 605775.33 | N100: 107194.6
A101: STR-1025 | B101: 45748 | C101: West | D101: Mall | E101: 55101.1 | F101: 5281 | G101: 0.189 | H101: 11 | I101: 91 | J101: 2.7 | K101: 0 | L101: 4.4 | M101: 675177.68 | N101: 105628.68
A102: STR-1026 | B102: 45658 | C102: East | D102: Mall | E102: 53084.76 | F102: 3642 | G102: 0.15 | H102: 12 | I102: 91.4 | J102: 0.2 | K102: 0 | L102: 4.4 | M102: 635181.35 | N102: 83341.25
A103: STR-1026 | B103: 45689 | C103: East | D103: Mall | E103: 63101.59 | F103: 4373 | G103: 0.173 | H103: 14 | I103: 90.4 | J103: 7.87 | K103: 0 | L103: 4.7 | M103: 586626.94 | N103: 86498.55
A104: STR-1026 | B104: 45717 | C104: East | D104: Mall | E104: 90084.4 | F104: 6832 | G104: 0.185 | H104: 14 | I104: 80.5 | J104: 0.77 | K104: 1 | L104: 4.4 | M104: 740102.64 | N104: 114299.07
A105: STR-1026 | B105: 45748 | C105: East | D105: Mall | E105: 32266.64 | F105: 2414 | G105: 0.08 | H105: 7 | I105: 92.1 | J105: 1.48 | K105: 0 | L105: 5 | M105: 625514.04 | N105: 120685.08
A106: STR-1027 | B106: 45658 | C106: West | D106: High Street | E106: 57919.07 | F106: 7374 | G106: 0.103 | H106: 21 | I106: 82.3 | J106: 2.87 | K106: 0 | L106: 2.9 | M106: 727227.2 | N106: 121292.01
A107: STR-1027 | B107: 45689 | C107: West | D107: High Street | E107: 74679.35 | F107: 8739 | G107: 0.056 | H107: 21 | I107: 91.8 | J107: 2.83 | K107: 0 | L107: 3 | M107: 783797.89 | N107: 157620.7
A108: STR-1027 | B108: 45717 | C108: West | D108: High Street | E108: 64294.23 | F108: 6992 | G108: 0.133 | H108: 14 | I108: 94.1 | J108: 0.25 | K108: 0 | L108: 3 | M108: 795153.84 | N108: 143194.21
A109: STR-1027 | B109: 45748 | C109: West | D109: High Street | E109: 31042.03 | F109: 7107 | G109: 0.051 | H109: 15 | I109: 87 | J109: 13.33 | K109: 0 | L109: 3.2 | M109: 665594.94 | N109: 127597.34
A110: STR-1028 | B110: 45658 | C110: East | D110: Mall | E110: 75265.02 | F110: 6975 | G110: 0.157 | H110: 20 | I110: 73.8 | J110: 6.35 | K110: 1 | L110: 3.8 | M110: 709478.39 | N110: 71294.27
A111: STR-1028 | B111: 45689 | C111: East | D111: Mall | E111: 69411.7 | F111: 5493 | G111: 0.292 | H111: 13 | I111: 86.5 | J111: 6.69 | K111: 0 | L111: 3.8 | M111: 664162.49 | N111: 98291.06
A112: STR-1028 | B112: 45717 | C112: East | D112: Mall | E112: 51056.15 | F112: 5686 | G112: 0.089 | H112: 13 | I112: 89.9 | J112: 1.28 | K112: 0 | L112: 4.2 | M112: 633494.21 | N112: 105739.47
... A134: STR-1034 | B134: 45658 | C134: North | D134: High Street | E134: 70276.28 | F134: 3043 | G134: 0.079 | H134: 9 | I134: 87.9 | J134: 3.77 | K134: 0 | L134: 4.4 | M134: 527300.13 | N134: 84197.87
A135: STR-1034 | B135: 45689 | C135: North | D135: High Street | E135: 22071.64 | F135: 1814 | G135: 0.196 | H135: 8 | I135: 81.1 | J135: 0.78 | K135: 0 | M135: 400831.65 | N135: 70979.31
A136: STR-1034 | B136: 45717 | C136: North | D136: High Street | E136: 52285.45 | F136: 3618 | G136: 0.086 | H136: 11 | I136: 95.6 | J136: 5.17 | K136: 1 | L136: 4.4 | M136: 593247.25 | N136: 81240.29
A137: STR-1034 | B137: 45748 | C137: North | D137: High Street | E137: 70366.76 | F137: 1963 | G137: 0.182 | H137: 8 | I137: 89.8 | J137: 3.2 | K137: 0 | L137: 4.6 | M137: 529075.95 | N137: 95978.83
A138: STR-1035 | B138: 45658 | C138: South | D138: Residential | E138: 71320.66 | F138: 7888 | G138: 0.048 | H138: 20 | I138: 78.1 | J138: 3.4 | K138: 0 | M138: 633638.03 | N138: 99402.01
A139: STR-1035 | B139: 45689 | C139: South | D139: Residential | E139: 75109.67 | F139: 6244 | G139: 0.079 | H139: 15 | I139: 96.3 | J139: 7.38 | K139: 0 | L139: 3.7 | M139: 743348.84 | N139: 104186.09
A140: STR-1035 | B140: 45717 | C140: South | D140: Residential | E140: 69779 | F140: 6544 | G140: 0.152 | H140: 18 | I140: 90.2 | J140: 0.85 | K140: 1 | L140: 3.3 | M140: 758827.64 | N140: 161439.48
A141: STR-1035 | B141: 45748 | C141: South | D141: Residential | E141: 44211.95 | F141: 5465 | G141: 0.187 | H141: 12 | I141: 90 | J141: 2.89 | K141: 0 | L141: 3.6 | M141: 646559.71 | N141: 97981.75
A142: STR-1036 | B142: 45658 | C142: West | D142: High Street | E142: 51430.31 | F142: 6427 | G142: 0.234 | H142: 14 | I142: 88.8 | J142: 0.77 | K142: 0 | L142: 4.1 | M142: 715890.53 | N142: 109032.15
A143: STR-1036 | B143: 45689 | C143: West | D143: High Street | E143: 45706.49 | F143: 6704 | G143: 0.038 | H143: 15 | I143: 94.2 | J143: 2.92 | K143: 0 | L143: 4.2 | M143: 715097.57 | N143: 151875.86
A144: STR-1036 | B144: 45717 | C144: West | D144: High Street | E144: 44034.6 | F144: 5645 | G144: 0.069 | H144: 18 | I144: 88.5 | J144: 3.07 | K144: 0 | L144: 3.8 | M144: 682639.28 | N144: 77557.53
A145: STR-1036 | B145: 45748 | C145: West | D145: High Street | E145: 50198.12 | F145: 6089 | G145: 0.182 | H145: 19 | I145: 94 | J145: 9.7 | K145: 0 | L145: 3.9 | M145: 695098.51 | N145: 108192.75
A146: STR-1037 | B146: 45658 | C146: North | D146: Residential | E146: 70488.2 | F146: 4312 | G146: 0.169 | H146: 12 | I146: 90.2 | J146: 3.71 | K146: 0 | L146: 3.2 | M146: 577732.57 | N146: 93804.27
A147: STR-1037 | B147: 45689 | C147: North | D147: Residential | E147: 50909.27 | F147: 3152 | G147: 0.06 | H147: 13 | I147: 93.7 | J147: 10.79 | K147: 0 | L147: 3.5 | M147: 537058.33 | N147: 93555.71
A148: STR-1037 | B148: 45717 | C148: North | D148: Residential | E148: 53351.7 | F148: 4259 | G148: 0.156 | H148: 15 | I148: 93.7 | J148: 6.03 | K148: 0 | L148: 3.4 | M148: 601568.87 | N148: 91634.82
A149: STR-1037 | B149: 45748 | C149: North | D149: Residential | E149: 60322.4 | F149: 3350 | G149: 0.108 | H149: 12 | I149: 89.4 | J149: 4.92 | K149: 0 | L149: 3.4 | M149: 570964.84 | N149: 81331.07
A150: STR-1038 | B150: 45658 | C150: South | D150: Mall | E150: 51575.68 | F150: 5329 | G150: 0.047 | H150: 17 | I150: 88.1 | J150: 19.78 | K150: 0 | L150: 3.8 | M150: 614024.91 | N150: 84828.93
... A163: STR-1041 | B163: 45689 | C163: South | D163: High Street | E163: 48438.85 | F163: 6992 | G163: 0.034 | H163: 20 | I163: 91 | J163: 4.36 | K163: 0 | L163: 4.2 | M163: 778298.88 | N163: 130076.72
A164: STR-1041 | B164: 45717 | C164: South | D164: High Street | E164: 57143.3 | F164: 8038 | G164: 0.193 | H164: 17 | I164: 72.6 | K164: 0 | L164: 4.2 | M164: 677096.71 | N164: 97174.11
A165: STR-1041 | B165: 45748 | C165: South | D165: High Street | E165: 66870.62 | F165: 6055 | G165: 0.075 | H165: 19 | I165: 93.8 | J165: 0.54 | K165: 0 | L165: 4.3 | M165: 692008.64 | N165: 116337.87
A166: STR-1042 | B166: 45658 | C166: North | D166: Mall | E166: 72150.53 | F166: 9323 | G166: 0.157 | H166: 22 | I166: 82.9 | J166: 11.37 | K166: 1 | L166: 4.3 | M166: 825797.91 | N166: 130945.24
A167: STR-1042 | B167: 45689 | C167: North | D167: Mall | E167: 35303.3 | F167: 8789 | G167: 0.123 | H167: 22 | I167: 86.1 | J167: 9.43 | K167: 0 | L167: 4.2 | M167: 706285.52 | N167: 138014.72
A168: STR-1042 | B168: 45717 | C168: North | D168: Mall | E168: 30301.86 | F168: 6939 | G168: 0.09 | H168: 16 | I168: 90.3 | J168: 3.49 | K168: 0 | L168: 4 | M168: 665534.7 | N168: 113167.73
A169: STR-1042 | B169: 45748 | C169: North | D169: Mall | E169: 78432.14 | F169: 9440 | G169: 0.126 | H169: 23 | I169: 89.2 | J169: 7.86 | K169: 0 | L169: 4.1 | M169: 820729.29 | N169: 159325.47
A170: STR-1043 | B170: 45658 | C170: East | D170: Residential | E170: 62059.18 | F170: 9374 | G170: 0.136 | H170: 25 | I170: 87.1 | J170: 12.55 | K170: 0 | L170: 4.9 | M170: 739831.73 | N170: 119490.21
A171: STR-1043 | B171: 45689 | C171: East | D171: Residential | E171: 32834.48 | F171: 7576 | G171: 0.099 | H171: 15 | I171: 84.1 | J171: 3.48 | K171: 0 | L171: 5 | M171: 593637.14 | N171: 106648.14
A172: STR-1043 | B172: 45717 | C172: East | D172: Residential | E172: 50825.08 | F172: 8949 | G172: 0.157 | H172: 21 | I172: 84.7 | J172: 7.73 | K172: 0 | L172: 4.9 | M172: 769702.76 | N172: 158697
A173: STR-1043 | B173: 45748 | C173: East | D173: Residential | E173: 36606.51 | F173: 7671 | G173: 0.118 | H173: 18 | I173: 89.8 | J173: 0.25 | K173: 0 | L173: 4.4 | M173: 679731.57 | N173: 121546.42
A174: STR-1044 | B174: 45658 | C174: East | D174: Residential | E174: 65237.79 | F174: 8741 | G174: 0.157 | H174: 20 | I174: 94.4 | J174: 6.43 | K174: 0 | L174: 3.3 | M174: 780344.18 | N174: 118239.09
A175: STR-1044 | B175: 45689 | C175: East | D175: Residential | E175: 43645.98 | F175: 9480 | G175: 0.109 | H175: 22 | I175: 89 | J175: 2.11 | K175: 0 | L175: 3.1 | M175: 721364.11 | N175: 147272.81
A176: STR-1044 | B176: 45717 | C176: East | D176: Residential | E176: 68040.15 | F176: 9826 | G176: 0.125 | H176: 20 | I176: 83.9 | J176: 9.12 | K176: 0 | L176: 3.6 | M176: 758138.29 | N176: 132975.26
... A196: STR-1049 | B196: 45717 | C196: West | D196: Residential | E196: 40220.18 | F196: 3783 | G196: 0.089 | H196: 14 | I196: 86.6 | J196: 3.63 | K196: 0 | L196: 3.7 | M196: 559422.02 | N196: 73528.74
...

Sheet Marketing_Regression
A1: SIMPLE REGRESSION ANALYSIS - MARKETING SPEND VS MONTHLY SALES
A3: SUMMARY OUTPUT
A5: Regression Statistics
A6: Multiple R | B6: 0.40895561
A7: R Square | B7: 0.16724469
A8: Adjusted R Square | B8: 0.16462596
A9: Standard Error | B9: 94846.034
A10: Observations | B10: 320
A12: ANOVA
B13: df | C13: SS | D13: MS | E13: F | F13: Significance F
A14: Regression | B14: 1 | C14: 5.7451371e+11 | D14: 5.7451371e+11 | E14: 63.864873 | F14: 2.4800615e-14
A15: Residual | B15: 318 | C15: 2.8606549e+12 | D15: 8.9957701e+09
A16: Total | B16: 319 | C16: 3.4351686e+12
B18: Coefficients | C18: Standard Error | D18: t Stat | E18: P-value | F18: Lower 95% | G18: Upper 95% | H18: Lower 95.0% | I18: Upper 95.0%
A19: Intercept | B19: 560777.35 | C19: 15906.906 | D19: 35.253703 | E19: 6.9528769e-112 | F19: 529481.27 | G19: 592073.42 | H19: 529481.27 | I19: 592073.42
A20: marketing_spend | B20: 2.1295753 | C20: 0.26647838 | D20: 7.9915501 | E20: 2.4800615e-14 | F20: 1.6052919 | G20: 2.6538587 | H20: 1.6052919 | I20: 2.6538587
A22: Key Findings: • Marketing Spend has a positive relationship with Monthly Sales. • Coefficient = 2.13, indicating higher marketing investment is associated with higher sales. • P-value is below 0.05, showing statistical significance. • R² = 0.167, meaning Marketing Spend explains approximately 16.7% of sales variation. • Marketing Spend is useful but not sufficient alone to explain store sales performance.

Sheet Simple_Regression
A1: SIMPLE REGRESSION ANALYSIS - FOOTFALL VS MONTHLY SALES
A3: SUMMARY OUTPUT
A5: Regression Statistics
A6: Multiple R | B6: 0.85807071
A7: R Square | B7: 0.73628534
A8: Adjusted R Square | B8: 0.73545605
A9: Standard Error | B9: 53373.736
A10: Observations | B10: 320
A12: ANOVA
B13: df | C13: SS | D13: MS | E13: F | F13: Significance F
A14: Regression | B14: 1 | C14: 2.5292643e+12 | D14: 2.5292643e+12 | E14: 887.84878 | F14: 4.7503615e-94
A15: Residual | B15: 318 | C15: 9.0590432e+11 | D15: 2.8487557e+09
A16: Total | B16: 319 | C16: 3.4351686e+12
B18: Coefficients | C18: Standard Error | D18: t Stat | E18: P-value | F18: Lower 95% | G18: Upper 95% | H18: Lower 95.0% | I18: Upper 95.0%
A19: Intercept | B19: 446410.58 | C19: 8407.7383 | D19: 53.095205 | E19: 4.0862696e-160 | F19: 429868.76 | G19: 462952.4 | H19: 429868.76 | I19: 462952.4
A20: footfall | B20: 35.678031 | C20: 1.1973783 | D20: 29.796791 | E20: 4.7503615e-94 | F20: 33.322247 | G20: 38.033815 | H20: 33.322247 | I20: 38.033815
A22: Key Findings: • Footfall is strongly associated with Monthly Sales. • Coefficient = 35.68 indicates each additional customer visit increases expected sales. • P-value is effectively zero, showing strong statistical significance. • R² = 0.736, meaning Footfall explains approximately 73.6% of sales variation. • Footfall is a stronger predictor than Marketing Spend.

Sheet Cleaned_Data
A1: store_id | B1: month | C1: region | D1: store_type | E1: marketing_spend | F1: footfall | G1: avg_discount_pct | H1: staff_count | I1: inventory_availability_pct | J1: competitor_distance_km | K1: holiday_flag | L1: customer_rating | M1: monthly_sales | N1: monthly_profit | O1: Region_North | P1: Region_South | Q1: Region_East
A2: STR-1001 | B2: 45658 | C2: East | D2: Residential | E2: 70389.11 | F2: 8302 | G2: 0.042 | H2: 17 | I2: 75 | J2: 5.28 | K2: 1 | L2: 3.1 | M2: 658832.62 | N2: 84349.93 | O2: 0 | P2: 0 | Q2: 1
A3: STR-1001 | B3: 45689 | C3: East | D3: Residential | E3: 43827.89 | F3: 8487 | G3: 0.168 | H3: 23 | I3: 84.4 | J3: 4.31 | K3: 0 | L3: 2.8 | M3: 634436 | N3: 106130.54 | O3: 0 | P3: 0 | Q3: 1
A4: STR-1001 | B4: 45717 | C4: East | D4: Residential | E4: 59921.75 | F4: 9113 | G4: 0.133 | H4: 20 | I4: 88 | J4: 12 | K4: 0 | L4: 3.2 | M4: 678722.06 | N4: 101883.86 | O4: 0 | P4: 0 | Q4: 1
A5: STR-1001 | B5: 45748 | C5: East | D5: Residential | E5: 56856.63 | F5: 9431 | G5: 0.142 | H5: 23 | I5: 86.9 | J5: 4.97 | K5: 0 | L5: 3.4 | M5: 658920.3 | N5: 97910.37 | O5: 0 | P5: 0 | Q5: 1
A6: STR-1002 | B6: 45658 | C6: East | D6: High Street | E6: 48412.64 | F6: 9545 | G6: 0.231 | H6: 21 | I6: 97.6 | J6: 6.94 | K6: 1 | L6: 4.2 | M6: 741341.44 | N6: 119208.17 | O6: 0 | P6: 0 | Q6: 1
A7: STR-1002 | B7: 45689 | C7: East | D7: High Street | E7: 64811.21 | F7: 9792 | G7: 0.112 | H7: 20 | I7: 84.2 | J7: 2.88 | K7: 0 | L7: 4.2 | M7: 761835.34 | N7: 149602.23 | O7: 0 | P7: 0 | Q7: 1
A8: STR-1002 | B8: 45717 | C8: East | D8: High Street | E8: 46213.45 | F8: 10616 | G8: 0.122 | H8: 22 | I8: 85.2 | J8: 0.2 | K8: 1 | L8: 4.1 | M8: 806615.54 | N8: 131364.62 | O8: 0 | P8: 0 | Q8: 1
A9: STR-1002 | B9: 45748 | C9: East | D9: High Street | E9: 68148.52 | F9: 8567 | G9: 0.127 | H9: 23 | I9: 95.6 | J9: 0.8 | K9: 0 | L9: 3.9 | M9: 850164.26 | N9: 149262.75 | O9: 0 | P9: 0 | Q9: 1
A10: STR-1003 | B10: 45658 | C10: North | D10: Airport | E10: 71838.86 | F10: 10979 | G10: 0.215 | H10: 26 | I10: 88.6 | J10: 7.7 | K10: 1 | L10: 3.8 | M10: 930581.7 | N10: 136207.98 | O10: 1 | P10: 0 | Q10: 0
A11: STR-1003 | B11: 45689 | C11: North | D11: Airport | E11: 68133.44 | F11: 9459 | G11: 0.22 | H11: 21 | I11: 85 | J11: 1.91 | K11: 0 | L11: 4.2 | M11: 779010.94 | N11: 106328.09 | O11: 1 | P11: 0 | Q11: 0
A12: STR-1003 | B12: 45717 | C12: North | D12: Airport | E12: 34285.21 | F12: 9172 | G12: 0.213 | H12: 22 | I12: 88.3 | J12: 10.46 | K12: 1 | L12: 3.8 | M12: 723060.76 | N12: 123131.24 | O12: 1 | P12: 0 | Q12: 0
A13: STR-1003 | B13: 45748 | C13: North | D13: Airport | E13: 67979.88 | F13: 11230 | G13: 0.002 | H13: 28 | I13: 85.3 | J13: 7.16 | K13: 0 | L13: 3.8 | M13: 910791.94 | N13: 158891.28 | O13: 1 | P13: 0 | Q13: 0
... A321: STR-1080 | B321: 45748 | C321: East | D321: Residential | E321: 40553.11 | F321: 5317 | G321: 0.165 | H321: 17 | I321: 84.3 | J321: 11.82 | K321: 0 | L321: 4.1 | M321: 559660.84 | N321: 71443.61 | O321: 0 | P321: 0 | Q321: 1
J322: =COUNTBLANK(J2:J321) -> 0 | K322: =COUNTBLANK(K2:K321) -> 0 | L322: =COUNTBLANK(L2:L321) -> 0

Sheet Dummy_Variables
A1: REGION DUMMY VARIABLE CREATION
A3: region | B3: Region_North | C3: Region_South | D3: Region_East
A4: East | B4: =IF($A4="North",1,0) -> 0 | C4: =IF($A4="South",1,0) -> 0 | D4: =IF($A4="East",1,0) -> 1
A5: East | B5: =IF($A5="North",1,0) -> 0 | C5: =IF($A5="South",1,0) -> 0 | D5: =IF($A5="East",1,0) -> 1
A6: East | B6: =IF($A6="North",1,0) -> 0 | C6: =IF($A6="South",1,0) -> 0 | D6: =IF($A6="East",1,0) -> 1
A7: East | B7: =IF($A7="North",1,0) -> 0 | C7: =IF($A7="South",1,0) -> 0 | D7: =IF($A7="East",1,0) -> 1
A8: East | B8: =IF($A8="North",1,0) -> 0 | C8: =IF($A8="South",1,0) -> 0 | D8: =IF($A8="East",1,0) -> 1
A9: East | B9: =IF($A9="North",1,0) -> 0 | C9: =IF($A9="South",1,0) -> 0 | D9: =IF($A9="East",1,0) -> 1 | F9: Reference Category: West Dummy Variables Created: • Region_North • Region_South • Region_East When all dummy variables = 0, the store belongs to the West region. This approach avoids the dummy variable trap.
A10: East | B10: =IF($A10="North",1,0) -> 0 | C10: =IF($A10="South",1,0) -> 0 | D10: =IF($A10="East",1,0) -> 1
A11: East | B11: =IF($A11="North",1,0) -> 0 | C11: =IF($A11="South",1,0) -> 0 | D11: =IF($A11="East",1,0) -> 1
A12: North | B12: =IF($A12="North",1,0) -> 1 | C12: =IF($A12="South",1,0) -> 0 | D12: =IF($A12="East",1,0) -> 0
A13: North | B13: =IF($A13="North",1,0) -> 1 | C13: =IF($A13="South",1,0) -> 0 | D13: =IF($A13="East",1,0) -> 0
A14: North | B14: =IF($A14="North",1,0) -> 1 | C14: =IF($A14="South",1,0) -> 0 | D14: =IF($A14="East",1,0) -> 0
A15: North | B15: =IF($A15="North",1,0) -> 1 | C15: =IF($A15="South",1,0) -> 0 | D15: =IF($A15="East",1,0) -> 0
A16: East | B16: =IF($A16="North",1,0) -> 0 | C16: =IF($A16="South",1,0) -> 0 | D16: =IF($A16="East",1,0) -> 1
A17: East | B17: =IF($A17="North",1,0) -> 0 | C17: =IF($A17="South",1,0) -> 0 | D17: =IF($A17="East",1,0) -> 1
A18: East | B18: =IF($A18="North",1,0) -> 0 | C18: =IF($A18="South",1,0) -> 0 | D18: =IF($A18="East",1,0) -> 1
A19: East | B19: =IF($A19="North",1,0) -> 0 | C19: =IF($A19="South",1,0) -> 0 | D19: =IF($A19="East",1,0) -> 1
A20: South | B20: =IF($A20="North",1,0) -> 0 | C20: =IF($A20="South",1,0) -> 1 | D20: =IF($A20="East",1,0) -> 0
A21: South | B21: =IF($A21="North",1,0) -> 0 | C21: =IF($A21="South",1,0) -> 1 | D21: =IF($A21="East",1,0) -> 0
... A323: East | B323: =IF($A323="North",1,0) -> 0 | C323: =IF($A323="South",1,0) -> 0 | D323: =IF($A323="East",1,0) -> 1

Sheet Multiple_Regression
A1: MULTIPLE REGRESSION ANALYSIS - MONTHLY SALES MODEL
A3: SUMMARY OUTPUT
A5: Regression Statistics
A6: Multiple R | B6: 0.90241558
A7: R Square | B7: 0.81435389
A8: Adjusted R Square | B8: 0.81018875
A9: Standard Error | B9: 45210.537
A10: Observations | B10: 320
A12: ANOVA
B13: df | C13: SS | D13: MS | E13: F | F13: Significance F
A14: Regression | B14: 7 | C14: 2.7974429e+12 | D14: 3.996347e+11 | E14: 195.5167 | F14: 4.6445309e-110
A15: Residual | B15: 312 | C15: 6.377257e+11 | D15: 2.0439926e+09
A16: Total | B16: 319 | C16: 3.4351686e+12
B18: Coefficients | C18: Standard Error | D18: t Stat | E18: P-value | F18: Lower 95% | G18: Upper 95% | H18: Lower 95.0% | I18: Upper 95.0%
A19: Intercept | B19: 98015.505 | C19: 49240.19 | D19: 1.990559 | E19: 0.047401555 | F19: 1130.6797 | G19: 194900.33 | H19: 1130.6797 | I19: 194900.33
A20: marketing_spend | B20: 1.2022734 | C20: 0.13108107 | D20: 9.1719835 | E20: 6.4895961e-18 | F20: 0.94435873 | G20: 1.460188 | H20: 0.94435873 | I20: 1.460188
A21: footfall | B21: 33.984257 | C21: 1.0501163 | D21: 32.362375 | E21: 1.0011259e-101 | F21: 31.918051 | G21: 36.050462 | H21: 31.918051 | I21: 36.050462
A22: inventory_availability_pct | B22: 2886.7347 | C22: 475.77927 | D22: 6.0673822 | E22: 3.7620281e-09 | F22: 1950.5931 | G22: 3822.8763 | H22: 1950.5931 | I22: 3822.8763
A23: customer_rating | B23: 11024.991 | C23: 4944.7476 | D23: 2.2296366 | E23: 0.026483017 | F23: 1295.7224 | G23: 20754.259 | H23: 1295.7224 | I23: 20754.259
A24: Region_North | B24: -8375.7106 | C24: 7393.5749 | D24: -1.1328364 | E24: 0.25815277 | F24: -22923.283 | G24: 6171.8615 | H24: -22923.283 | I24: 6171.8615
A25: Region_South | B25: 4929.5867 | C25: 7513.8352 | D25: 0.65606798 | E25: 0.51226391 | F25: -9854.6091 | G25: 19713.783 | H25: -9854.6091 | I25: 19713.783
A26: Region_East | B26: -17042.833 | C26: 6518.0764 | D26: -2.6147029 | E26: 0.0093640864 | F26: -29867.778 | G26: -4217.889 | H26: -29867.778 | I26: -4217.889
A29: Key Findings: • Multiple Regression achieved the highest explanatory power (R² = 0.814). • Footfall is the strongest predictor of Monthly Sales. • Marketing Spend and Customer Rating positively influence sales. • Region_East shows significantly lower sales compared to the reference region. • Inventory Availability, Region_North, and Region_South are not statistically significant. • This model was selected as the final business recommendation model.

Sheet Regression_Input_Data
A1: MULTIPLE REGRESSION INPUT DATASET
A3: monthly_sales | B3: marketing_spend | C3: footfall | D3: inventory_availability_pct | E3: customer_rating | F3: Region_North | G3: Region_South | H3: Region_East
A4: 658832.62 | B4: 70389.11 | C4: 8302 | D4: 75 | E4: 3.1 | F4: 0 | G4: 0 | H4: 1
A5: 634436 | B5: 43827.89 | C5: 8487 | D5: 84.4 | E5: 2.8 | F5: 0 | G5: 0 | H5: 1
A6: 678722.06 | B6: 59921.75 | C6: 9113 | D6: 88 | E6: 3.2 | F6: 0 | G6: 0 | H6: 1
A7: 658920.3 | B7: 56856.63 | C7: 9431 | D7: 86.9 | E7: 3.4 | F7: 0 | G7: 0 | H7: 1 | J7: This dataset was prepared for multiple regression analysis. It includes numerical predictors and region dummy variables used in the final model.
A8: 741341.44 | B8: 48412.64 | C8: 9545 | D8: 97.6 | E8: 4.2 | F8: 0 | G8: 0 | H8: 1
A9: 761835.34 | B9: 64811.21 | C9: 9792 | D9: 84.2 | E9: 4.2 | F9: 0 | G9: 0 | H9: 1
A10: 806615.54 | B10: 46213.45 | C10: 10616 | D10: 85.2 | E10: 4.1 | F10: 0 | G10: 0 | H10: 1
A11: 850164.26 | B11: 68148.52 | C11: 8567 | D11: 95.6 | E11: 3.9 | F11: 0 | G11: 0 | H11: 1
A12: 930581.7 | B12: 71838.86 | C12: 10979 | D12: 88.6 | E12: 3.8 | F12: 1 | G12: 0 | H12: 0
A13: 779010.94 | B13: 68133.44 | C13: 9459 | D13: 85 | E13: 4.2 | F13: 1 | G13: 0 | H13: 0
A14: 723060.76 | B14: 34285.21 | C14: 9172 | D14: 88.3 | E14: 3.8 | F14: 1 | G14: 0 | H14: 0
A15: 910791.94 | B15: 67979.88 | C15: 11230 | D15: 85.3 | E15: 3.8 | F15: 1 | G15: 0 | H15: 0
A16: 922168.6 | B16: 71828.26 | C16: 12775 | D16: 81.7 | E16: 4.2 | F16: 0 | G16: 0 | H16: 1
A17: 726606.28 | B17: 55716.82 | C17: 10054 | D17: 84.9 | E17: 4.3 | F17: 0 | G17: 0 | H17: 1
A18: 746501.09 | B18: 59909.51 | C18: 8895 | D18: 88.8 | E18: 4.3 | F18: 0 | G18: 0 | H18: 1
A19: 834017.02 | B19: 75305.71 | C19: 10940 | D19: 76.5 | E19: 4.5 | F19: 0 | G19: 0 | H19: 1
... A323: 559660.84 | B323: 40553.11 | C323: 5317 | D323: 84.3 | E323: 4.1 | F323: 0 | G323: 0 | H323: 1
E324: =COUNTBLANK(E4:E323) -> 0

Sheet Predictions_Residuals
A1: PREDICTED SALES AND RESIDUAL ANALYSIS
F3: TOP 5 POSITIVE RESIDUALS
A4: Actual_Sales | B4: Predicted_Sales | C4: Residual
A5: 685379.08 | B5: =98015.50529 +(1.202273376*Cleaned_Data!E68) +(33.98425653*Cleaned_Data!F68) +(2886.7347*Cleaned_Data!I68) +(11024.99051*Cleaned_Data!L68) +(-8375.710551*Cleaned_Data!O68) +(4929.586703*Cleaned_Data!P68) +(-17042.83335*Cleaned_Data!Q68) -> 841678.34 | C5: =A5-B5 -> -156299.26 | F5: Actual Sales | G5: Predicted Sales | H5: Residual
A6: 595467.6 | B6: =98015.50529 +(1.202273376*Cleaned_Data!E46) +(33.98425653*Cleaned_Data!F46) +(2886.7347*Cleaned_Data!I46) +(11024.99051*Cleaned_Data!L46) +(-8375.710551*Cleaned_Data!O46) +(4929.586703*Cleaned_Data!P46) +(-17042.83335*Cleaned_Data!Q46) -> 729696.76 | C6: =A6-B6 -> -134229.16 | F6: 799046.94 | G6: 706026.96 | H6: 93019.98
A7: 627171.9 | B7: =98015.50529 +(1.202273376*Cleaned_Data!E91) +(33.98425653*Cleaned_Data!F91) +(2886.7347*Cleaned_Data!I91) +(11024.99051*Cleaned_Data!L91) +(-8375.710551*Cleaned_Data!O91) +(4929.586703*Cleaned_Data!P91) +(-17042.83335*Cleaned_Data!Q91) -> 757388.58 | C7: =A7-B7 -> -130216.68 | F7: 813316.71 | G7: 718839.53 | H7: 94477.18
A8: 641865.03 | B8: =98015.50529 +(1.202273376*Cleaned_Data!E34) +(33.98425653*Cleaned_Data!F34) +(2886.7347*Cleaned_Data!I34) +(11024.99051*Cleaned_Data!L34) +(-8375.710551*Cleaned_Data!O34) +(4929.586703*Cleaned_Data!P34) +(-17042.83335*Cleaned_Data!Q34) -> 762488.83 | C8: =A8-B8 -> -120623.8 | F8: 787715.51 | G8: 687127.02 | H8: 100588.5
A9: 538376 | B9: =98015.50529 +(1.202273376*Cleaned_Data!E307) +(33.98425653*Cleaned_Data!F307) +(2886.7347*Cleaned_Data!I307) +(11024.99051*Cleaned_Data!L307) +(-8375.710551*Cleaned_Data!O307) +(4929.586703*Cleaned_Data!P307) +(-17042.83335*Cleaned_Data!Q307) -> 648422.32 | C9: =A9-B9 -> -110046.32 | F9: 625514.04 | G9: 522797.21 | H9: 102716.8
A10: 415721.82 | B10: =98015.50529 +(1.202273376*Cleaned_Data!E22) +(33.98425653*Cleaned_Data!F22) +(2886.7347*Cleaned_Data!I22) +(11024.99051*Cleaned_Data!L22) +(-8375.710551*Cleaned_Data!O22) +(4929.586703*Cleaned_Data!P22) +(-17042.83335*Cleaned_Data!Q22) -> 521959.97 | C10: =A10-B10 -> -106238.15 | F10: 713611.16 | G10: 585781.3 | H10: 127829.9
A11: 800451.94 | B11: =98015.50529 +(1.202273376*Cleaned_Data!E27) +(33.98425653*Cleaned_Data!F27) +(2886.7347*Cleaned_Data!I27) +(11024.99051*Cleaned_Data!L27) +(-8375.710551*Cleaned_Data!O27) +(4929.586703*Cleaned_Data!P27) +(-17042.83335*Cleaned_Data!Q27) -> 900517.55 | C11: =A11-B11 -> -100065.61
A12: 658920.3 | B12: =98015.50529 +(1.202273376*Cleaned_Data!E5) +(33.98425653*Cleaned_Data!F5) +(2886.7347*Cleaned_Data!I5) +(11024.99051*Cleaned_Data!L5) +(-8375.710551*Cleaned_Data!O5) +(4929.586703*Cleaned_Data!P5) +(-17042.83335*Cleaned_Data!Q5) -> 758177.62 | C12: =A12-B12 -> -99257.321
A13: 463534.25 | B13: =98015.50529 +(1.202273376*Cleaned_Data!E54) +(33.98425653*Cleaned_Data!F54) +(2886.7347*Cleaned_Data!I54) +(11024.99051*Cleaned_Data!L54) +(-8375.710551*Cleaned_Data!O54) +(4929.586703*Cleaned_Data!P54) +(-17042.83335*Cleaned_Data!Q54) -> 559538.16 | C13: =A13-B13 -> -96003.907
A14: 449465.06 | B14: =98015.50529 +(1.202273376*Cleaned_Data!E197) +(33.98425653*Cleaned_Data!F197) +(2886.7347*Cleaned_Data!I197) +(11024.99051*Cleaned_Data!L197) +(-8375.710551*Cleaned_Data!O197) +(4929.586703*Cleaned_Data!P197) +(-17042.83335*Cleaned_Data!Q197) -> 544385.13 | C14: =A14-B14 -> -94920.067 | F14: TOP 5 NEGATIVE RESIDUALS
A15: 633638.03 | B15: =98015.50529 +(1.202273376*Cleaned_Data!E138) +(33.98425653*Cleaned_Data!F138) +(2886.7347*Cleaned_Data!I138) +(11024.99051*Cleaned_Data!L138) +(-8375.710551*Cleaned_Data!O138) +(4929.586703*Cleaned_Data!P138) +(-17042.83335*Cleaned_Data!Q138) -> 725431.78 | C15: =A15-B15 -> -91793.751
A16: 673076.34 | B16: =98015.50529 +(1.202273376*Cleaned_Data!E278) +(33.98425653*Cleaned_Data!F278) +(2886.7347*Cleaned_Data!I278) +(11024.99051*Cleaned_Data!L278) +(-8375.710551*Cleaned_Data!O278) +(4929.586703*Cleaned_Data!P278) +(-17042.83335*Cleaned_Data!Q278) -> 758053.24 | C16: =A16-B16 -> -84976.896 | F16: Actual Sales | G16: Predicted Sales | H16: Residual
A17: 684217.32 | B17: =98015.50529 +(1.202273376*Cleaned_Data!E120) +(33.98425653*Cleaned_Data!F120) +(2886.7347*Cleaned_Data!I120) +(11024.99051*Cleaned_Data!L120) +(-8375.710551*Cleaned_Data!O120) +(4929.586703*Cleaned_Data!P120) +(-17042.83335*Cleaned_Data!Q120) -> 768435.36 | C17: =A17-B17 -> -84218.042 | F17: 685379.08 | G17: 841678.34 | H17: =F17-G17 -> -156299.26
A18: 593637.14 | B18: =98015.50529 +(1.202273376*Cleaned_Data!E171) +(33.98425653*Cleaned_Data!F171) +(2886.7347*Cleaned_Data!I171) +(11024.99051*Cleaned_Data!L171) +(-8375.710551*Cleaned_Data!O171) +(4929.586703*Cleaned_Data!P171) +(-17042.83335*Cleaned_Data!Q171) -> 675812.76 | C18: =A18-B18 -> -82175.621 | F18: 595467.6 | G18: 729696.76 | H18: =F18-G18 -> -134229.16
A19: 678722.06 | B19: =98015.50529 +(1.202273376*Cleaned_Data!E4) +(33.98425653*Cleaned_Data!F4) +(2886.7347*Cleaned_Data!I4) +(11024.99051*Cleaned_Data!L4) +(-8375.710551*Cleaned_Data!O4) +(4929.586703*Cleaned_Data!P4) +(-17042.83335*Cleaned_Data!Q4) -> 752026.15 | C19: =A19-B19 -> -73304.09 | F19: 627171.9 | G19: 757388.58 | H19: =F19-G19 -> -130216.68
A20: 511844.41 | B20: =98015.50529 +(1.202273376*Cleaned_Data!E30) +(33.98425653*Cleaned_Data!F30) +(2886.7347*Cleaned_Data!I30) +(11024.99051*Cleaned_Data!L30) +(-8375.710551*Cleaned_Data!O30) +(4929.586703*Cleaned_Data!P30) +(-17042.83335*Cleaned_Data!Q30) -> 584041 | C20: =A20-B20 -> -72196.591 | F20: 641865.03 | G20: 762488.83 | H20: =F20-G20 -> -120623.8
A21: 427917.38 | B21: =98015.50529 +(1.202273376*Cleaned_Data!E33) +(33.98425653*Cleaned_Data!F33) +(2886.7347*Cleaned_Data!I33) +(11024.99051*Cleaned_Data!L33) +(-8375.710551*Cleaned_Data!O33) +(4929.586703*Cleaned_Data!P33) +(-17042.83335*Cleaned_Data!Q33) -> 497117.14 | C21: =A21-B21 -> -69199.759 | F21: 538376 | G21: 648422.32 | H21: =F21-G21 -> -110046.32
A22: 401582.58 | B22: =98015.50529 +(1.202273376*Cleaned_Data!E301) +(33.98425653*Cleaned_Data!F301) +(2886.7347*Cleaned_Data!I301) +(11024.99051*Cleaned_Data!L301) +(-8375.710551*Cleaned_Data!O301) +(4929.586703*Cleaned_Data!P301) +(-17042.83335*Cleaned_Data!Q301) -> 470056.83 | C22: =A22-B22 -> -68474.249
A23: 721079.35 | B23: =98015.50529 +(1.202273376*Cleaned_Data!E238) +(33.98425653*Cleaned_Data!F238) +(2886.7347*Cleaned_Data!I238) +(11024.99051*Cleaned_Data!L238) +(-8375.710551*Cleaned_Data!O238) +(4929.586703*Cleaned_Data!P238) +(-17042.83335*Cleaned_Data!Q238) -> 789498.25 | C23: =A23-B23 -> -68418.898
A24: 691288.19 | B24: =98015.50529 +(1.202273376*Cleaned_Data!E211) +(33.98425653*Cleaned_Data!F211) +(2886.7347*Cleaned_Data!I211) +(11024.99051*Cleaned_Data!L211) +(-8375.710551*Cleaned_Data!O211) +(4929.586703*Cleaned_Data!P211) +(-17042.83335*Cleaned_Data!Q211) -> 759544.76 | C24: =A24-B24 -> -68256.573
A25: 630829.94 | B25: =98015.50529 +(1.202273376*Cleaned_Data!E75) +(33.98425653*Cleaned_Data!F75) +(2886.7347*Cleaned_Data!I75) +(11024.99051*Cleaned_Data!L75) +(-8375.710551*Cleaned_Data!O75) +(4929.586703*Cleaned_Data!P75) +(-17042.83335*Cleaned_Data!Q75) -> 699012.07 | C25: =A25-B25 -> -68182.134
A26: 441275.42 | B26: =98015.50529 +(1.202273376*Cleaned_Data!E125) +(33.98425653*Cleaned_Data!F125) +(2886.7347*Cleaned_Data!I125) +(11024.99051*Cleaned_Data!L125) +(-8375.710551*Cleaned_Data!O125) +(4929.586703*Cleaned_Data!P125) +(-17042.83335*Cleaned_Data!Q125) -> 508165.91 | C26: =A26-B26 -> -66890.494
A27: 651164.18 | B27: =98015.50529 +(1.202273376*Cleaned_Data!E309) +(33.98425653*Cleaned_Data!F309) +(2886.7347*Cleaned_Data!I309) +(11024.99051*Cleaned_Data!L309) +(-8375.710551*Cleaned_Data!O309) +(4929.586703*Cleaned_Data!P309) +(-17042.83335*Cleaned_Data!Q309) -> 717743.37 | C27: =A27-B27 -> -66579.189
A28: 660633.99 | B28: =98015.50529 +(1.202273376*Cleaned_Data!E270) +(33.98425653*Cleaned_Data!F270) +(2886.7347*Cleaned_Data!I270) +(11024.99051*Cleaned_Data!L270) +(-8375.710551*Cleaned_Data!O270) +(4929.586703*Cleaned_Data!P270) +(-17042.83335*Cleaned_Data!Q270) -> 726869.33 | C28: =A28-B28 -> -66235.342
A29: 675917.63 | B29: =98015.50529 +(1.202273376*Cleaned_Data!E209) +(33.98425653*Cleaned_Data!F209) +(2886.7347*Cleaned_Data!I209) +(11024.99051*Cleaned_Data!L209) +(-8375.710551*Cleaned_Data!O209) +(4929.586703*Cleaned_Data!P209) +(-17042.83335*Cleaned_Data!Q209) -> 741959.63 | C29: =A29-B29 -> -66042.003
A30: 799477.76 | B30: =98015.50529 +(1.202273376*Cleaned_Data!E35) +(33.98425653*Cleaned_Data!F35) +(2886.7347*Cleaned_Data!I35) +(11024.99051*Cleaned_Data!L35) +(-8375.710551*Cleaned_Data!O35) +(4929.586703*Cleaned_Data!P35) +(-17042.83335*Cleaned_Data!Q35) -> 863504.07 | C30: =A30-B30 -> -64026.31
A31: 725235.28 | B31: =98015.50529 +(1.202273376*Cleaned_Data!E132) +(33.98425653*Cleaned_Data!F132) +(2886.7347*Cleaned_Data!I132) +(11024.99051*Cleaned_Data!L132) +(-8375.710551*Cleaned_Data!O132) +(4929.586703*Cleaned_Data!P132) +(-17042.83335*Cleaned_Data!Q132) -> 789253.5 | C31: =A31-B31 -> -64018.225
A32: 634436 | B32: =98015.50529 +(1.202273376*Cleaned_Data!E3) +(33.98425653*Cleaned_Data!F3) +(2886.7347*Cleaned_Data!I3) +(11024.99051*Cleaned_Data!L3) +(-8375.710551*Cleaned_Data!O3) +(4929.586703*Cleaned_Data!P3) +(-17042.83335*Cleaned_Data!Q3) -> 696600.54 | C32: =A32-B32 -> -62164.544
A33: 593343 | B33: =98015.50529 +(1.202273376*Cleaned_Data!E273) +(33.98425653*Cleaned_Data!F273) +(2886.7347*Cleaned_Data!I273) +(11024.99051*Cleaned_Data!L273) +(-8375.710551*Cleaned_Data!O273) +(4929.586703*Cleaned_Data!P273) +(-17042.83335*Cleaned_Data!Q273) -> 653416.57 | C33: =A33-B33 -> -60073.575
A34: 650480.06 | B34: =98015.50529 +(1.202273376*Cleaned_Data!E162) +(33.98425653*Cleaned_Data!F162) +(2886.7347*Cleaned_Data!I162) +(11024.99051*Cleaned_Data!L162) +(-8375.710551*Cleaned_Data!O162) +(4929.586703*Cleaned_Data!P162) +(-17042.83335*Cleaned_Data!Q162) -> 710318.79 | C34: =A34-B34 -> -59838.731
A35: 620264.2 | B35: =98015.50529 +(1.202273376*Cleaned_Data!E318) +(33.98425653*Cleaned_Data!F318) +(2886.7347*Cleaned_Data!I318) +(11024.99051*Cleaned_Data!L318) +(-8375.710551*Cleaned_Data!O318) +(4929.586703*Cleaned_Data!P318) +(-17042.83335*Cleaned_Data!Q318) -> 676998.87 | C35: =A35-B35 -> -56734.667
A36: 726606.28 | B36: =98015.50529 +(1.202273376*Cleaned_Data!E15) +(33.98425653*Cleaned_Data!F15) +(2886.7347*Cleaned_Data!I15) +(11024.99051*Cleaned_Data!L15) +(-8375.710551*Cleaned_Data!O15) +(4929.586703*Cleaned_Data!P15) +(-17042.83335*Cleaned_Data!Q15) -> 782128.47 | C36: =A36-B36 -> -55522.192
A37: 400831.65 | B37: =98015.50529 +(1.202273376*Cleaned_Data!E135) +(33.98425653*Cleaned_Data!F135) +(2886.7347*Cleaned_Data!I135) +(11024.99051*Cleaned_Data!L135) +(-8375.710551*Cleaned_Data!O135) +(4929.586703*Cleaned_Data!P135) +(-17042.83335*Cleaned_Data!Q135) -> 455155.53 | C37: =A37-B37 -> -54323.878
A38: 527300.13 | B38: =98015.50529 +(1.202273376*Cleaned_Data!E134) +(33.98425653*Cleaned_Data!F134) +(2886.7347*Cleaned_Data!I134) +(11024.99051*Cleaned_Data!L134) +(-8375.710551*Cleaned_Data!O134) +(4929.586703*Cleaned_Data!P134) +(-17042.83335*Cleaned_Data!Q134) -> 579799.13 | C38: =A38-B38 -> -52498.996
A39: 536524.84 | B39: =98015.50529 +(1.202273376*Cleaned_Data!E311) +(33.98425653*Cleaned_Data!F311) +(2886.7347*Cleaned_Data!I311) +(11024.99051*Cleaned_Data!L311) +(-8375.710551*Cleaned_Data!O311) +(4929.586703*Cleaned_Data!P311) +(-17042.83335*Cleaned_Data!Q311) -> 588528.84 | C39: =A39-B39 -> -52004.003
A40: 509484.81 | B40: =98015.50529 +(1.202273376*Cleaned_Data!E122) +(33.98425653*Cleaned_Data!F122) +(2886.7347*Cleaned_Data!I122) +(11024.99051*Cleaned_Data!L122) +(-8375.710551*Cleaned_Data!O122) +(4929.586703*Cleaned_Data!P122) +(-17042.83335*Cleaned_Data!Q122) -> 561465.22 | C40: =A40-B40 -> -51980.412
A41: 643428.85 | B41: =98015.50529 +(1.202273376*Cleaned_Data!E194) +(33.98425653*Cleaned_Data!F194) +(2886.7347*Cleaned_Data!I194) +(11024.99051*Cleaned_Data!L194) +(-8375.710551*Cleaned_Data!O194) +(4929.586703*Cleaned_Data!P194) +(-17042.83335*Cleaned_Data!Q194) -> 695302.25 | C41: =A41-B41 -> -51873.4
A42: 524899.57 | B42: =98015.50529 +(1.202273376*Cleaned_Data!E282) +(33.98425653*Cleaned_Data!F282) +(2886.7347*Cleaned_Data!I282) +(11024.99051*Cleaned_Data!L282) +(-8375.710551*Cleaned_Data!O282) +(4929.586703*Cleaned_Data!P282) +(-17042.83335*Cleaned_Data!Q282) -> 576356.62 | C42: =A42-B42 -> -51457.054
A43: 671868.59 | B43: =98015.50529 +(1.202273376*Cleaned_Data!E208) +(33.98425653*Cleaned_Data!F208) +(2886.7347*Cleaned_Data!I208) +(11024.99051*Cleaned_Data!L208) +(-8375.710551*Cleaned_Data!O208) +(4929.586703*Cleaned_Data!P208) +(-17042.83335*Cleaned_Data!Q208) -> 723083.69 | C43: =A43-B43 -> -51215.098
A44: 741341.44 | B44: =98015.50529 +(1.202273376*Cleaned_Data!E6) +(33.98425653*Cleaned_Data!F6) +(2886.7347*Cleaned_Data!I6) +(11024.99051*Cleaned_Data!L6) +(-8375.710551*Cleaned_Data!O6) +(4929.586703*Cleaned_Data!P6) +(-17042.83335*Cleaned_Data!Q6) -> 791607.9 | C44: =A44-B44 -> -50266.456
A45: 599603.4 | B45: =98015.50529 +(1.202273376*Cleaned_Data!E47) +(33.98425653*Cleaned_Data!F47) +(2886.7347*Cleaned_Data!I47) +(11024.99051*Cleaned_Data!L47) +(-8375.710551*Cleaned_Data!O47) +(4929.586703*Cleaned_Data!P47) +(-17042.83335*Cleaned_Data!Q47) -> 649305.71 | C45: =A45-B45 -> -49702.305
A46: 554012.07 | B46: =98015.50529 +(1.202273376*Cleaned_Data!E193) +(33.98425653*Cleaned_Data!F193) +(2886.7347*Cleaned_Data!I193) +(11024.99051*Cleaned_Data!L193) +(-8375.710551*Cleaned_Data!O193) +(4929.586703*Cleaned_Data!P193) +(-17042.83335*Cleaned_Data!Q193) -> 601932.74 | C46: =A46-B46 -> -47920.67
A47: 570963.31 | B47: =98015.50529 +(1.202273376*Cleaned_Data!E230) +(33.98425653*Cleaned_Data!F230) +(2886.7347*Cleaned_Data!I230) +(11024.99051*Cleaned_Data!L230) +(-8375.710551*Cleaned_Data!O230) +(4929.586703*Cleaned_Data!P230) +(-17042.83335*Cleaned_Data!Q230) -> 618156.29 | C47: =A47-B47 -> -47192.981
A48: 680840.36 | B48: =98015.50529 +(1.202273376*Cleaned_Data!E77) +(33.98425653*Cleaned_Data!F77) +(2886.7347*Cleaned_Data!I77) +(11024.99051*Cleaned_Data!L77) +(-8375.710551*Cleaned_Data!O77) +(4929.586703*Cleaned_Data!P77) +(-17042.83335*Cleaned_Data!Q77) -> 727606.13 | C48: =A48-B48 -> -46765.767
A49: 688368.46 | B49: =98015.50529 +(1.202273376*Cleaned_Data!E315) +(33.98425653*Cleaned_Data!F315) +(2886.7347*Cleaned_Data!I315) +(11024.99051*Cleaned_Data!L315) +(-8375.710551*Cleaned_Data!O315) +(4929.586703*Cleaned_Data!P315) +(-17042.83335*Cleaned_Data!Q315) -> 733704.59 | C49: =A49-B49 -> -45336.134
A50: 546223.7 | B50: =98015.50529 +(1.202273376*Cleaned_Data!E294) +(33.98425653*Cleaned_Data!F294) +(2886.7347*Cleaned_Data!I294) +(11024.99051*Cleaned_Data!L294) +(-8375.710551*Cleaned_Data!O294) +(4929.586703*Cleaned_Data!P294) +(-17042.83335*Cleaned_Data!Q294) -> 590717.29 | C50: =A50-B50 -> -44493.592
A51: 487464.91 | B51: =98015.50529 +(1.202273376*Cleaned_Data!E57) +(33.98425653*Cleaned_Data!F57) +(2886.7347*Cleaned_Data!I57) +(11024.99051*Cleaned_Data!L57) +(-8375.710551*Cleaned_Data!O57) +(4929.586703*Cleaned_Data!P57) +(-17042.83335*Cleaned_Data!Q57) -> 531733.84 | C51: =A51-B51 -> -44268.931
A52: 578949.84 | B52: =98015.50529 +(1.202273376*Cleaned_Data!E200) +(33.98425653*Cleaned_Data!F200) +(2886.7347*Cleaned_Data!I200) +(11024.99051*Cleaned_Data!L200) +(-8375.710551*Cleaned_Data!O200) +(4929.586703*Cleaned_Data!P200) +(-17042.83335*Cleaned_Data!Q200) -> 621134.58 | C52: =A52-B52 -> -42184.74
A53: 574066.61 | B53: =98015.50529 +(1.202273376*Cleaned_Data!E199) +(33.98425653*Cleaned_Data!F199) +(2886.7347*Cleaned_Data!I199) +(11024.99051*Cleaned_Data!L199) +(-8375.710551*Cleaned_Data!O199) +(4929.586703*Cleaned_Data!P199) +(-17042.83335*Cleaned_Data!Q199) -> 615194.34 | C53: =A53-B53 -> -41127.734
A54: 697287.9 | B54: =98015.50529 +(1.202273376*Cleaned_Data!E116) +(33.98425653*Cleaned_Data!F116) +(2886.7347*Cleaned_Data!I116) +(11024.99051*Cleaned_Data!L116) +(-8375.710551*Cleaned_Data!O116) +(4929.586703*Cleaned_Data!P116) +(-17042.83335*Cleaned_Data!Q116) -> 737980.21 | C54: =A54-B54 -> -40692.306
A55: 739831.73 | B55: =98015.50529 +(1.202273376*Cleaned_Data!E170) +(33.98425653*Cleaned_Data!F170) +(2886.7347*Cleaned_Data!I170) +(11024.99051*Cleaned_Data!L170) +(-8375.710551*Cleaned_Data!O170) +(4929.586703*Cleaned_Data!P170) +(-17042.83335*Cleaned_Data!Q170) -> 779610.24 | C55: =A55-B55 -> -39778.508
A56: 685830.24 | B56: =98015.50529 +(1.202273376*Cleaned_Data!E156) +(33.98425653*Cleaned_Data!F156) +(2886.7347*Cleaned_Data!I156) +(11024.99051*Cleaned_Data!L156) +(-8375.710551*Cleaned_Data!O156) +(4929.586703*Cleaned_Data!P156) +(-17042.83335*Cleaned_Data!Q156) -> 725595.46 | C56: =A56-B56 -> -39765.219
A57: 658832.62 | B57: =98015.50529 +(1.202273376*Cleaned_Data!E2) +(33.98425653*Cleaned_Data!F2) +(2886.7347*Cleaned_Data!I2) +(11024.99051*Cleaned_Data!L2) +(-8375.710551*Cleaned_Data!O2) +(4929.586703*Cleaned_Data!P2) +(-17042.83335*Cleaned_Data!Q2) -> 698419.5 | C57: =A57-B57 -> -39586.876
A58: 559660.84 | B58: =98015.50529 +(1.202273376*Cleaned_Data!E321) +(33.98425653*Cleaned_Data!F321) +(2886.7347*Cleaned_Data!I321) +(11024.99051*Cleaned_Data!L321) +(-8375.710551*Cleaned_Data!O321) +(4929.586703*Cleaned_Data!P321) +(-17042.83335*Cleaned_Data!Q321) -> 598977.08 | C58: =A58-B58 -> -39316.245
A59: 607084.92 | B59: =98015.50529 +(1.202273376*Cleaned_Data!E204) +(33.98425653*Cleaned_Data!F204) +(2886.7347*Cleaned_Data!I204) +(11024.99051*Cleaned_Data!L204) +(-8375.710551*Cleaned_Data!O204) +(4929.586703*Cleaned_Data!P204) +(-17042.83335*Cleaned_Data!Q204) -> 646025.13 | C59: =A59-B59 -> -38940.207
A60: 577732.57 | B60: =98015.50529 +(1.202273376*Cleaned_Data!E146) +(33.98425653*Cleaned_Data!F146) +(2886.7347*Cleaned_Data!I146) +(11024.99051*Cleaned_Data!L146) +(-8375.710551*Cleaned_Data!O146) +(4929.586703*Cleaned_Data!P146) +(-17042.83335*Cleaned_Data!Q146) -> 616589.43 | C60: =A60-B60 -> -38856.865
A61: 573155.19 | B61: =98015.50529 +(1.202273376*Cleaned_Data!E19) +(33.98425653*Cleaned_Data!F19) +(2886.7347*Cleaned_Data!I19) +(11024.99051*Cleaned_Data!L19) +(-8375.710551*Cleaned_Data!O19) +(4929.586703*Cleaned_Data!P19) +(-17042.83335*Cleaned_Data!Q19) -> 611463.78 | C61: =A61-B61 -> -38308.59
A62: 611766.72 | B62: =98015.50529 +(1.202273376*Cleaned_Data!E87) +(33.98425653*Cleaned_Data!F87) +(2886.7347*Cleaned_Data!I87) +(11024.99051*Cleaned_Data!L87) +(-8375.710551*Cleaned_Data!O87) +(4929.586703*Cleaned_Data!P87) +(-17042.83335*Cleaned_Data!Q87) -> 648930.94 | C62: =A62-B62 -> -37164.22
A63: 555557.77 | B63: =98015.50529 +(1.202273376*Cleaned_Data!E283) +(33.98425653*Cleaned_Data!F283) +(2886.7347*Cleaned_Data!I283) +(11024.99051*Cleaned_Data!L283) +(-8375.710551*Cleaned_Data!O283) +(4929.586703*Cleaned_Data!P283) +(-17042.83335*Cleaned_Data!Q283) -> 590595.03 | C63: =A63-B63 -> -35037.261
A64: 666573.2 | B64: =98015.50529 +(1.202273376*Cleaned_Data!E20) +(33.98425653*Cleaned_Data!F20) +(2886.7347*Cleaned_Data!I20) +(11024.99051*Cleaned_Data!L20) +(-8375.710551*Cleaned_Data!O20) +(4929.586703*Cleaned_Data!P20) +(-17042.83335*Cleaned_Data!Q20) -> 700565.66 | C64: =A64-B64 -> -33992.46
A65: 696261.49 | B65: =98015.50529 +(1.202273376*Cleaned_Data!E291) +(33.98425653*Cleaned_Data!F291) +(2886.7347*Cleaned_Data!I291) +(11024.99051*Cleaned_Data!L291) +(-8375.710551*Cleaned_Data!O291) +(4929.586703*Cleaned_Data!P291) +(-17042.83335*Cleaned_Data!Q291) -> 729713.09 | C65: =A65-B65 -> -33451.596
A66: 636561.34 | B66: =98015.50529 +(1.202273376*Cleaned_Data!E81) +(33.98425653*Cleaned_Data!F81) +(2886.7347*Cleaned_Data!I81) +(11024.99051*Cleaned_Data!L81) +(-8375.710551*Cleaned_Data!O81) +(4929.586703*Cleaned_Data!P81) +(-17042.83335*Cleaned_Data!Q81) -> 669715.74 | C66: =A66-B66 -> -33154.404
A67: 596969.27 | B67: =98015.50529 +(1.202273376*Cleaned_Data!E232) +(33.98425653*Cleaned_Data!F232) +(2886.7347*Cleaned_Data!I232) +(11024.99051*Cleaned_Data!L232) +(-8375.710551*Cleaned_Data!O232) +(4929.586703*Cleaned_Data!P232) +(-17042.83335*Cleaned_Data!Q232) -> 629921.66 | C67: =A67-B67 -> -32952.389
A68: 800979.78 | B68: =98015.50529 +(1.202273376*Cleaned_Data!E37) +(33.98425653*Cleaned_Data!F37) +(2886.7347*Cleaned_Data!I37) +(11024.99051*Cleaned_Data!L37) +(-8375.710551*Cleaned_Data!O37) +(4929.586703*Cleaned_Data!P37) +(-17042.83335*Cleaned_Data!Q37) -> 833453.77 | C68: =A68-B68 -> -32473.989
A69: 718330.53 | B69: =98015.50529 +(1.202273376*Cleaned_Data!E39) +(33.98425653*Cleaned_Data!F39) +(2886.7347*Cleaned_Data!I39) +(11024.99051*Cleaned_Data!L39) +(-8375.710551*Cleaned_Data!O39) +(4929.586703*Cleaned_Data!P39) +(-17042.83335*Cleaned_Data!Q39) -> 750521.73 | C69: =A69-B69 -> -32191.204
A70: 586626.94 | B70: =98015.50529 +(1.202273376*Cleaned_Data!E103) +(33.98425653*Cleaned_Data!F103) +(2886.7347*Cleaned_Data!I103) +(11024.99051*Cleaned_Data!L103) +(-8375.710551*Cleaned_Data!O103) +(4929.586703*Cleaned_Data!P103) +(-17042.83335*Cleaned_Data!Q103) -> 618229.46 | C70: =A70-B70 -> -31602.52
A71: 557487.26 | B71: =98015.50529 +(1.202273376*Cleaned_Data!E124) +(33.98425653*Cleaned_Data!F124) +(2886.7347*Cleaned_Data!I124) +(11024.99051*Cleaned_Data!L124) +(-8375.710551*Cleaned_Data!O124) +(4929.586703*Cleaned_Data!P124) +(-17042.83335*Cleaned_Data!Q124) -> 588528.17 | C71: =A71-B71 -> -31040.907
A72: 612390.14 | B72: =98015.50529 +(1.202273376*Cleaned_Data!E257) +(33.98425653*Cleaned_Data!F257) +(2886.7347*Cleaned_Data!I257) +(11024.99051*Cleaned_Data!L257) +(-8375.710551*Cleaned_Data!O257) +(4929.586703*Cleaned_Data!P257) +(-17042.83335*Cleaned_Data!Q257) -> 643343.72 | C72: =A72-B72 -> -30953.577
A73: 537058.33 | B73: =98015.50529 +(1.202273376*Cleaned_Data!E147) +(33.98425653*Cleaned_Data!F147) +(2886.7347*Cleaned_Data!I147) +(11024.99051*Cleaned_Data!L147) +(-8375.710551*Cleaned_Data!O147) +(4929.586703*Cleaned_Data!P147) +(-17042.83335*Cleaned_Data!Q147) -> 567039.54 | C73: =A73-B73 -> -29981.209
A74: 553756.43 | B74: =98015.50529 +(1.202273376*Cleaned_Data!E61) +(33.98425653*Cleaned_Data!F61) +(2886.7347*Cleaned_Data!I61) +(11024.99051*Cleaned_Data!L61) +(-8375.710551*Cleaned_Data!O61) +(4929.586703*Cleaned_Data!P61) +(-17042.83335*Cleaned_Data!Q61) -> 583326.85 | C74: =A74-B74 -> -29570.422
A75: 666152.52 | B75: =98015.50529 +(1.202273376*Cleaned_Data!E18) +(33.98425653*Cleaned_Data!F18) +(2886.7347*Cleaned_Data!I18) +(11024.99051*Cleaned_Data!L18) +(-8375.710551*Cleaned_Data!O18) +(4929.586703*Cleaned_Data!P18) +(-17042.83335*Cleaned_Data!Q18) -> 695407.1 | C75: =A75-B75 -> -29254.583
A76: 548103.7 | B76: =98015.50529 +(1.202273376*Cleaned_Data!E289) +(33.98425653*Cleaned_Data!F289) +(2886.7347*Cleaned_Data!I289) +(11024.99051*Cleaned_Data!L289) +(-8375.710551*Cleaned_Data!O289) +(4929.586703*Cleaned_Data!P289) +(-17042.83335*Cleaned_Data!Q289) -> 577141.42 | C76: =A76-B76 -> -29037.72
A77: 622811.74 | B77: =98015.50529 +(1.202273376*Cleaned_Data!E50) +(33.98425653*Cleaned_Data!F50) +(2886.7347*Cleaned_Data!I50) +(11024.99051*Cleaned_Data!L50) +(-8375.710551*Cleaned_Data!O50) +(4929.586703*Cleaned_Data!P50) +(-17042.83335*Cleaned_Data!Q50) -> 651847.04 | C77: =A77-B77 -> -29035.296
A78: 617291.15 | B78: =98015.50529 +(1.202273376*Cleaned_Data!E60) +(33.98425653*Cleaned_Data!F60) +(2886.7347*Cleaned_Data!I60) +(11024.99051*Cleaned_Data!L60) +(-8375.710551*Cleaned_Data!O60) +(4929.586703*Cleaned_Data!P60) +(-17042.83335*Cleaned_Data!Q60) -> 646232.32 | C78: =A78-B78 -> -28941.169
A79: 718074.79 | B79: =98015.50529 +(1.202273376*Cleaned_Data!E117) +(33.98425653*Cleaned_Data!F117) +(2886.7347*Cleaned_Data!I117) +(11024.99051*Cleaned_Data!L117) +(-8375.710551*Cleaned_Data!O117) +(4929.586703*Cleaned_Data!P117) +(-17042.83335*Cleaned_Data!Q117) -> 746989.06 | C79: =A79-B79 -> -28914.267
A80: 607898.12 | B80: =98015.50529 +(1.202273376*Cleaned_Data!E97) +(33.98425653*Cleaned_Data!F97) +(2886.7347*Cleaned_Data!I97) +(11024.99051*Cleaned_Data!L97) +(-8375.710551*Cleaned_Data!O97) +(4929.586703*Cleaned_Data!P97) +(-17042.83335*Cleaned_Data!Q97) -> 636575.6 | C80: =A80-B80 -> -28677.476
A81: 614024.91 | B81: =98015.50529 +(1.202273376*Cleaned_Data!E150) +(33.98425653*Cleaned_Data!F150) +(2886.7347*Cleaned_Data!I150) +(11024.99051*Cleaned_Data!L150) +(-8375.710551*Cleaned_Data!O150) +(4929.586703*Cleaned_Data!P150) +(-17042.83335*Cleaned_Data!Q150) -> 642271.55 | C81: =A81-B81 -> -28246.643
A82: 761122.42 | B82: =98015.50529 +(1.202273376*Cleaned_Data!E281) +(33.98425653*Cleaned_Data!F281) +(2886.7347*Cleaned_Data!I281) +(11024.99051*Cleaned_Data!L281) +(-8375.710551*Cleaned_Data!O281) +(4929.586703*Cleaned_Data!P281) +(-17042.83335*Cleaned_Data!Q281) -> 788946.72 | C82: =A82-B82 -> -27824.303
A83: 723531.4 | B83: =98015.50529 +(1.202273376*Cleaned_Data!E225) +(33.98425653*Cleaned_Data!F225) +(2886.7347*Cleaned_Data!I225) +(11024.99051*Cleaned_Data!L225) +(-8375.710551*Cleaned_Data!O225) +(4929.586703*Cleaned_Data!P225) +(-17042.83335*Cleaned_Data!Q225) -> 750863.3 | C83: =A83-B83 -> -27331.903
A84: 621369.58 | B84: =98015.50529 +(1.202273376*Cleaned_Data!E82) +(33.98425653*Cleaned_Data!F82) +(2886.7347*Cleaned_Data!I82) +(11024.99051*Cleaned_Data!L82) +(-8375.710551*Cleaned_Data!O82) +(4929.586703*Cleaned_Data!P82) +(-17042.83335*Cleaned_Data!Q82) -> 647977.95 | C84: =A84-B84 -> -26608.368
A85: 585937.48 | B85: =98015.50529 +(1.202273376*Cleaned_Data!E94) +(33.98425653*Cleaned_Data!F94) +(2886.7347*Cleaned_Data!I94) +(11024.99051*Cleaned_Data!L94) +(-8375.710551*Cleaned_Data!O94) +(4929.586703*Cleaned_Data!P94) +(-17042.83335*Cleaned_Data!Q94) -> 611795.5 | C85: =A85-B85 -> -25858.019
A86: 591619.95 | B86: =98015.50529 +(1.202273376*Cleaned_Data!E21) +(33.98425653*Cleaned_Data!F21) +(2886.7347*Cleaned_Data!I21) +(11024.99051*Cleaned_Data!L21) +(-8375.710551*Cleaned_Data!O21) +(4929.586703*Cleaned_Data!P21) +(-17042.83335*Cleaned_Data!Q21) -> 617101.67 | C86: =A86-B86 -> -25481.715
A87: 721364.11 | B87: =98015.50529 +(1.202273376*Cleaned_Data!E175) +(33.98425653*Cleaned_Data!F175) +(2886.7347*Cleaned_Data!I175) +(11024.99051*Cleaned_Data!L175) +(-8375.710551*Cleaned_Data!O175) +(4929.586703*Cleaned_Data!P175) +(-17042.83335*Cleaned_Data!Q175) -> 746714.68 | C87: =A87-B87 -> -25350.572
A88: 628538.3 | B88: =98015.50529 +(1.202273376*Cleaned_Data!E310) +(33.98425653*Cleaned_Data!F310) +(2886.7347*Cleaned_Data!I310) +(11024.99051*Cleaned_Data!L310) +(-8375.710551*Cleaned_Data!O310) +(4929.586703*Cleaned_Data!P310) +(-17042.83335*Cleaned_Data!Q310) -> 653618.57 | C88: =A88-B88 -> -25080.274
A89: 621677.3 | B89: =98015.50529 +(1.202273376*Cleaned_Data!E312) +(33.98425653*Cleaned_Data!F312) +(2886.7347*Cleaned_Data!I312) +(11024.99051*Cleaned_Data!L312) +(-8375.710551*Cleaned_Data!O312) +(4929.586703*Cleaned_Data!P312) +(-17042.83335*Cleaned_Data!Q312) -> 646624.69 | C89: =A89-B89 -> -24947.39
A90: 677096.71 | B90: =98015.50529 +(1.202273376*Cleaned_Data!E164) +(33.98425653*Cleaned_Data!F164) +(2886.7347*Cleaned_Data!I164) +(11024.99051*Cleaned_Data!L164) +(-8375.710551*Cleaned_Data!O164) +(4929.586703*Cleaned_Data!P164) +(-17042.83335*Cleaned_Data!Q164) -> 700694.31 | C90: =A90-B90 -> -23597.604
A91: 842439.67 | B91: =98015.50529 +(1.202273376*Cleaned_Data!E127) +(33.98425653*Cleaned_Data!F127) +(2886.7347*Cleaned_Data!I127) +(11024.99051*Cleaned_Data!L127) +(-8375.710551*Cleaned_Data!O127) +(4929.586703*Cleaned_Data!P127) +(-17042.83335*Cleaned_Data!Q127) -> 865428.82 | C91: =A91-B91 -> -22989.153
A92: 735480.19 | B92: =98015.50529 +(1.202273376*Cleaned_Data!E121) +(33.98425653*Cleaned_Data!F121) +(2886.7347*Cleaned_Data!I121) +(11024.99051*Cleaned_Data!L121) +(-8375.710551*Cleaned_Data!O121) +(4929.586703*Cleaned_Data!P121) +(-17042.83335*Cleaned_Data!Q121) -> 757802.16 | C92: =A92-B92 -> -22321.972
A93: 529075.95 | B93: =98015.50529 +(1.202273376*Cleaned_Data!E137) +(33.98425653*Cleaned_Data!F137) +(2886.7347*Cleaned_Data!I137) +(11024.99051*Cleaned_Data!L137) +(-8375.710551*Cleaned_Data!O137) +(4929.586703*Cleaned_Data!P137) +(-17042.83335*Cleaned_Data!Q137) -> 550894.7 | C93: =A93-B93 -> -21818.755
A94: 752321.72 | B94: =98015.50529 +(1.202273376*Cleaned_Data!E216) +(33.98425653*Cleaned_Data!F216) +(2886.7347*Cleaned_Data!I216) +(11024.99051*Cleaned_Data!L216) +(-8375.710551*Cleaned_Data!O216) +(4929.586703*Cleaned_Data!P216) +(-17042.83335*Cleaned_Data!Q216) -> 774045.87 | C94: =A94-B94 -> -21724.155
A95: 784502.68 | B95: =98015.50529 +(1.202273376*Cleaned_Data!E66) +(33.98425653*Cleaned_Data!F66) +(2886.7347*Cleaned_Data!I66) +(11024.99051*Cleaned_Data!L66) +(-8375.710551*Cleaned_Data!O66) +(4929.586703*Cleaned_Data!P66) +(-17042.83335*Cleaned_Data!Q66) -> 806042.1 | C95: =A95-B95 -> -21539.417
A96: 636775.66 | B96: =98015.50529 +(1.202273376*Cleaned_Data!E286) +(33.98425653*Cleaned_Data!F286) +(2886.7347*Cleaned_Data!I286) +(11024.99051*Cleaned_Data!L286) +(-8375.710551*Cleaned_Data!O286) +(4929.586703*Cleaned_Data!P286) +(-17042.83335*Cleaned_Data!Q286) -> 658130.09 | C96: =A96-B96 -> -21354.433
A97: 717141.55 | B97: =98015.50529 +(1.202273376*Cleaned_Data!E67) +(33.98425653*Cleaned_Data!F67) +(2886.7347*Cleaned_Data!I67) +(11024.99051*Cleaned_Data!L67) +(-8375.710551*Cleaned_Data!O67) +(4929.586703*Cleaned_Data!P67) +(-17042.83335*Cleaned_Data!Q67) -> 738367.52 | C97: =A97-B97 -> -21225.974
A98: 491905.13 | B98: =98015.50529 +(1.202273376*Cleaned_Data!E23) +(33.98425653*Cleaned_Data!F23) +(2886.7347*Cleaned_Data!I23) +(11024.99051*Cleaned_Data!L23) +(-8375.710551*Cleaned_Data!O23) +(4929.586703*Cleaned_Data!P23) +(-17042.83335*Cleaned_Data!Q23) -> 512620.23 | C98: =A98-B98 -> -20715.103
A99: 679230.86 | B99: =98015.50529 +(1.202273376*Cleaned_Data!E248) +(33.98425653*Cleaned_Data!F248) +(2886.7347*Cleaned_Data!I248) +(11024.99051*Cleaned_Data!L248) +(-8375.710551*Cleaned_Data!O248) +(4929.586703*Cleaned_Data!P248) +(-17042.83335*Cleaned_Data!Q248) -> 699750.81 | C99: =A99-B99 -> -20519.953
A100: 758138.29 | B100: =98015.50529 +(1.202273376*Cleaned_Data!E176) +(33.98425653*Cleaned_Data!F176) +(2886.7347*Cleaned_Data!I176) +(11024.99051*Cleaned_Data!L176) +(-8375.710551*Cleaned_Data!O176) +(4929.586703*Cleaned_Data!P176) +(-17042.83335*Cleaned_Data!Q176) -> 778591.84 | C100: =A100-B100 -> -20453.555
A101: 681855.56 | B101: =98015.50529 +(1.202273376*Cleaned_Data!E186) +(33.98425653*Cleaned_Data!F186) +(2886.7347*Cleaned_Data!I186) +(11024.99051*Cleaned_Data!L186) +(-8375.710551*Cleaned_Data!O186) +(4929.586703*Cleaned_Data!P186) +(-17042.83335*Cleaned_Data!Q186) -> 701890.51 | C101: =A101-B101 -> -20034.945
...
